saltaway/__init__.py
saltaway/api.py
saltaway/cli.py
saltaway/exceptions.py
saltaway/repositories.py
saltaway/utils.py
saltaway-0.2.0.dist-info/DESCRIPTION.rst
saltaway-0.2.0.dist-info/METADATA
saltaway-0.2.0.dist-info/RECORD
saltaway-0.2.0.dist-info/WHEEL
saltaway-0.2.0.dist-info/entry_points.txt
saltaway-0.2.0.dist-info/metadata.json
saltaway-0.2.0.dist-info/top_level.txt
